outcome/eventkit/__init__.py
outcome/eventkit/data/__init__.py
outcome/eventkit/data/coder.py
outcome/eventkit/data/data.py
outcome/eventkit/data/json.py
outcome/eventkit/dispatch.py
outcome/eventkit/event.py
outcome/eventkit/formats/__init__.py
outcome/eventkit/formats/format.py
outcome/eventkit/formats/json.py
outcome/eventkit/mime/__init__.py
outcome/eventkit/mime/mime.lark
outcome/eventkit/mime/mime.py
outcome/eventkit/protocol_bindings/__init__.py
outcome/eventkit/protocol_bindings/http.py
outcome/eventkit/py.typed
outcome_eventkit-0.3.3.dist-info/WHEEL
outcome_eventkit-0.3.3.dist-info/METADATA
outcome_eventkit-0.3.3.dist-info/RECORD
