Metadata-Version: 2.1
Name: outcome-eventkit
Version: 0.3.3
Summary: A toolkit for emitting and handling events, following the CloudEvent spec.
Home-page: https://github.com/outcome-co/eventkit-py
Author: Outcome Engineering
Author-email: engineering@outcome.co
Requires-Python: >=3.8.6,<3.9.0
Classifier: Programming Language :: Python :: 3
Requires-Dist: lark-parser (>=0.10.1,<0.12.0)
Requires-Dist: outcome-utils (>=5.0.0,<6.0.0)
Requires-Dist: pendulum (>=2.1.2,<3.0.0)
Requires-Dist: pydantic (>=1.7.2,<2.0.0)
Requires-Dist: requests (>=2.24.0,<3.0.0)
Project-URL: Documentation, https://github.com/outcome-co/eventkit-py#README
Project-URL: Repository, https://github.com/outcome-co/eventkit-py
